examples/__init__.py
examples/functional.py
examples/periodic.py
examples/polynomial.py
tests/__init__.py
tests/test_graph.py
Graft_Psy-1.0.0.dist-info/METADATA
Graft_Psy-1.0.0.dist-info/WHEEL
Graft_Psy-1.0.0.dist-info/top_level.txt
Graft_Psy-1.0.0.dist-info/RECORD
